Workbook

Sheet Реквизиты
A1: Реквизиты и данные клиента
A2: Заполните синие ячейки один раз — счёт и акт подставят данные сами.
A4: Исполнитель
A5: Наименование | B5: ИП Имаканов Руслан Арсланович
A6: ИИН | B6: 020413550395
A7: Адрес | B7: г. Костанай, ул. Тауелсиздик, 70
A8: Банк | B8: АО «Народный Банк Казахстана»
A9: ИИК | B9: KZ56601A221039793271
A10: БИК | B10: HSBKKZKX
A11: Кбе | B11: 19
A12: Телефон | B12: +7 707 611 30 75
A13: Почта | B13: ruslanimakanov8@gmail.com
A14: Заказчик (клиника)
A15: Наименование
A16: БИН/ИИН
A17: Адрес
A18: Документ
A19: Номер счёта | B19: 1
A20: Дата счёта | B20: =TODAY()
A21: Номер акта | B21: 1
A22: Дата акта | B22: =TODAY()
A23: Договор | B23: Публичная оферта https://puls-kliniki.imakanovr.workers.dev/terms
A25: Тарифы (справочник)
A26: Подписка «Старт», месяц | B26: 29000
A27: Подписка «Клиника», месяц | B27: 49000
A28: Подписка «Сеть», месяц | B28: 89000
A29: Подключение (разово) | B29: 150000

Sheet Счёт
A1: ="Счёт на оплату № "&Реквизиты!B19&" от "&TEXT(Реквизиты!B20,"DD.MM.YYYY")
A3: Поставщик | B3: =Реквизиты!B5&", ИИН "&Реквизиты!B6&", "&Реквизиты!B7
A4: Покупатель | B4: =Реквизиты!B15&IF(Реквизиты!B16<>"",", БИН/ИИН "&Реквизиты!B16,"")&IF(Реквизиты!B17<>"",", "&Реквизиты!B17,"")
A5: Договор | B5: =Реквизиты!B23
A7: № | B7: Наименование | C7: Кол-во | D7: Цена | E7: Сумма
A8: 1 | B8: Подписка на программу «Пульс клиники», тариф «Клиника», 1 месяц | C8: 1 | D8: =Реквизиты!B27 | E8: =IF(AND(ISNUMBER(C8),ISNUMBER(D8)),C8*D8,0)
A9: 2 | B9: Подключение: перенос данных, настройка, обучение | C9: 1 | D9: =Реквизиты!B29 | E9: =IF(AND(ISNUMBER(C9),ISNUMBER(D9)),C9*D9,0)
A10: 3 | E10: =IF(AND(ISNUMBER(C10),ISNUMBER(D10)),C10*D10,0)
A11: 4 | E11: =IF(AND(ISNUMBER(C11),ISNUMBER(D11)),C11*D11,0)
A12: 5 | E12: =IF(AND(ISNUMBER(C12),ISNUMBER(D12)),C12*D12,0)
D13: Итого | E13: =SUM(E8:E12)
D14: НДС | E14: без НДС
A16: Всего к оплате: | B16: =TEXT(E13,"#,##0")&" тенге"
A17: Сумма прописью: | B17: введите вручную, например: сто девяносто девять тысяч тенге 00 тиын
A19: Реквизиты для оплаты
A20: Получатель | B20: =Реквизиты!B5
A21: ИИН | B21: =Реквизиты!B6
A22: Банк | B22: =Реквизиты!B8
A23: ИИК | B23: =Реквизиты!B9
A24: БИК | B24: =Реквизиты!B10
A25: Кбе | B25: =Реквизиты!B11
A26: Назначение платежа | B26: ="Оплата по счёту № "&Реквизиты!B19&" от "&TEXT(Реквизиты!B20,"DD.MM.YYYY")&", подписка «Пульс клиники»"
A28: Счёт действителен 10 календарных дней. Подпись: ____________ / Имаканов Р. А. /

Sheet Акт
A1: ="Акт выполненных работ (оказанных услуг) № "&Реквизиты!B21&" от "&TEXT(Реквизиты!B22,"DD.MM.YYYY")
A3: Исполнитель | B3: =Реквизиты!B5&", ИИН "&Реквизиты!B6&", "&Реквизиты!B7
A4: Заказчик | B4: =Реквизиты!B15&IF(Реквизиты!B16<>"",", БИН/ИИН "&Реквизиты!B16,"")&IF(Реквизиты!B17<>"",", "&Реквизиты!B17,"")
A5: Договор | B5: =Реквизиты!B23
A7: № | B7: Наименование | C7: Кол-во | D7: Цена | E7: Сумма
A8: 1 | B8: Подписка на программу «Пульс клиники», тариф «Клиника», 1 месяц | C8: 1 | D8: =Реквизиты!B27 | E8: =IF(AND(ISNUMBER(C8),ISNUMBER(D8)),C8*D8,0)
A9: 2 | B9: Подключение: перенос данных, настройка, обучение | C9: 1 | D9: =Реквизиты!B29 | E9: =IF(AND(ISNUMBER(C9),ISNUMBER(D9)),C9*D9,0)
A10: 3 | E10: =IF(AND(ISNUMBER(C10),ISNUMBER(D10)),C10*D10,0)
A11: 4 | E11: =IF(AND(ISNUMBER(C11),ISNUMBER(D11)),C11*D11,0)
A12: 5 | E12: =IF(AND(ISNUMBER(C12),ISNUMBER(D12)),C12*D12,0)
D13: Итого | E13: =SUM(E8:E12)
D14: НДС | E14: без НДС
A16: Всего к оплате: | B16: =TEXT(E13,"#,##0")&" тенге"
A17: Сумма прописью: | B17: введите вручную, например: сто девяносто девять тысяч тенге 00 тиын
A19: Услуги оказаны в полном объёме и в срок. Заказчик претензий по объёму, качеству и срокам не имеет.
A21: Исполнитель: ____________ / Имаканов Р. А. /
A22: Заказчик: ____________ / _______________ /

Sheet Учёт обращений
A1: Клиника | B1: Город | C1: Страна | D1: Контакт (имя, должность) | E1: Почта / телефон | F1: Канал | G1: Дата 1-го письма | H1: Метка (utm) | I1: Ответ | J1: Статус | K1: Следующий шаг | L1: Когда | M1: Тариф | N1: Сумма, ₸ | O1: Дней с письма | P1: Нужно напомнить?
A2: MEDIKER | B2: Шымкент | C2: Казахстан | E2: pochta@mediker.kz | F2: Почта | G2: 46319 | H2: kz1 | J2: Написали | K2: Напомнить | L2: 46322 | O2: =IF(G2="","",TODAY()-G2) | P2: =IF(OR(G2="",J2="Оплатили",J2="Отказ",J2="Показ",J2="Пробный месяц"),"",IF(TODAY()-G2>=3,"да",""))
A3: Эмирмед | B3: Астана | C3: Казахстан | E3: emirmed@mail.ru | F3: Почта | G3: 46319 | H3: kz2 | J3: Написали | K3: Напомнить | L3: 46322 | O3: =IF(G3="","",TODAY()-G3) | P3: =IF(OR(G3="",J3="Оплатили",J3="Отказ",J3="Показ",J3="Пробный месяц"),"",IF(TODAY()-G3>=3,"да",""))
A4: AKFA Medline | B4: Ташкент | C4: Узбекистан | E4: info@akfamedline.uz | F4: Почта | G4: 46319 | H4: uz1 | J4: Написали | K4: Напомнить | L4: 46322 | O4: =IF(G4="","",TODAY()-G4) | P4: =IF(OR(G4="",J4="Оплатили",J4="Отказ",J4="Показ",J4="Пробный месяц"),"",IF(TODAY()-G4>=3,"да",""))
O5: =IF(G5="","",TODAY()-G5) | P5: =IF(OR(G5="",J5="Оплатили",J5="Отказ",J5="Показ",J5="Пробный месяц"),"",IF(TODAY()-G5>=3,"да",""))
O6: =IF(G6="","",TODAY()-G6) | P6: =IF(OR(G6="",J6="Оплатили",J6="Отказ",J6="Показ",J6="Пробный месяц"),"",IF(TODAY()-G6>=3,"да",""))
O7: =IF(G7="","",TODAY()-G7) | P7: =IF(OR(G7="",J7="Оплатили",J7="Отказ",J7="Показ",J7="Пробный месяц"),"",IF(TODAY()-G7>=3,"да",""))
O8: =IF(G8="","",TODAY()-G8) | P8: =IF(OR(G8="",J8="Оплатили",J8="Отказ",J8="Показ",J8="Пробный месяц"),"",IF(TODAY()-G8>=3,"да",""))
O9: =IF(G9="","",TODAY()-G9) | P9: =IF(OR(G9="",J9="Оплатили",J9="Отказ",J9="Показ",J9="Пробный месяц"),"",IF(TODAY()-G9>=3,"да",""))
O10: =IF(G10="","",TODAY()-G10) | P10: =IF(OR(G10="",J10="Оплатили",J10="Отказ",J10="Показ",J10="Пробный месяц"),"",IF(TODAY()-G10>=3,"да",""))
O11: =IF(G11="","",TODAY()-G11) | P11: =IF(OR(G11="",J11="Оплатили",J11="Отказ",J11="Показ",J11="Пробный месяц"),"",IF(TODAY()-G11>=3,"да",""))
O12: =IF(G12="","",TODAY()-G12) | P12: =IF(OR(G12="",J12="Оплатили",J12="Отказ",J12="Показ",J12="Пробный месяц"),"",IF(TODAY()-G12>=3,"да",""))
O13: =IF(G13="","",TODAY()-G13) | P13: =IF(OR(G13="",J13="Оплатили",J13="Отказ",J13="Показ",J13="Пробный месяц"),"",IF(TODAY()-G13>=3,"да",""))
O14: =IF(G14="","",TODAY()-G14) | P14: =IF(OR(G14="",J14="Оплатили",J14="Отказ",J14="Показ",J14="Пробный месяц"),"",IF(TODAY()-G14>=3,"да",""))
O15: =IF(G15="","",TODAY()-G15) | P15: =IF(OR(G15="",J15="Оплатили",J15="Отказ",J15="Показ",J15="Пробный месяц"),"",IF(TODAY()-G15>=3,"да",""))
O16: =IF(G16="","",TODAY()-G16) | P16: =IF(OR(G16="",J16="Оплатили",J16="Отказ",J16="Показ",J16="Пробный месяц"),"",IF(TODAY()-G16>=3,"да",""))
... O201: =IF(G201="","",TODAY()-G201) | P201: =IF(OR(G201="",J201="Оплатили",J201="Отказ",J201="Показ",J201="Пробный месяц"),"",IF(TODAY()-G201>=3,"да",""))

Sheet Воронка
A1: Воронка продаж
A2: Считается из листа «Учёт обращений».
A4: Статус | B4: Клиник | C4: Доля от написанных
A5: Написали | B5: =COUNTIF('Учёт обращений'!J2:J201,A5) | C5: =IF($B$11=0,0,B5/$B$11)
A6: Ответили | B6: =COUNTIF('Учёт обращений'!J2:J201,A6) | C6: =IF($B$11=0,0,B6/$B$11)
A7: Показ | B7: =COUNTIF('Учёт обращений'!J2:J201,A7) | C7: =IF($B$11=0,0,B7/$B$11)
A8: Пробный месяц | B8: =COUNTIF('Учёт обращений'!J2:J201,A8) | C8: =IF($B$11=0,0,B8/$B$11)
A9: Оплатили | B9: =COUNTIF('Учёт обращений'!J2:J201,A9) | C9: =IF($B$11=0,0,B9/$B$11)
A10: Отказ | B10: =COUNTIF('Учёт обращений'!J2:J201,A10) | C10: =IF($B$11=0,0,B10/$B$11)
A11: Всего | B11: =SUM(B5:B10)
A13: Получено, ₸ | B13: =SUMIF('Учёт обращений'!J2:J201,"Оплатили",'Учёт обращений'!N2:N201)
A14: Нужно напомнить сегодня | B14: =COUNTIF('Учёт обращений'!P2:P201,"да")
A15: Из написанных ответили (%) | B15: =IF(B11=0,0,(B6+B7+B8+B9+B10)/B11)
